{
  "325004990": "str. 31 August 1989",
  "325004999": "Bd. Ștefan cel Mare și Sfânt",
  "340052760": "Grădina Publică",
  "340052768": "Circul",
  "340052769": "Circ",
  "340052772": "bd. Grigore Vieru",
  "340052773": "str. Columna",
  "376339210": "Asociația \"Beton Armat\"",
  "376339213": "Asociația \"Agromașina\"",
  "376339215": "Asociația \"Agromașina\"",
  "376339225": "Asociaţia \"Cerealiere\"",
  "376339226": "Asociaţia \"Cerialiere\"",
  "376339230": "Asociaţia \"Tutun-CTC\"",
  "376339233": "Keramin",
  "376339234": "Keramin",
  "376339237": "Centrul Comercial \"Progres\"",
  "376339239": "Centrul Comercial \"Progres\"",
  "376339280": "str. Eugen Doga",
  "376339323": "str. Kiev",
  "376339350": "Dumitru Rîşcanu",
  "376339351": "Florării",
  "376339355": "Dumitru Rîşcanu",
  "461604330": "str. Romană",
  "461604331": "str. Romană",
  "1836506522": "str. Tudor Vladimirescu",
  "2144170985": "Florării",
  "4563611318": "Asociația \"Beton Armat\"",
  "4563611331": "Asociaţia \"Tutun-CTC\""
}
